fastapi_sitemap/__init__.py
fastapi_sitemap/__main__.py
fastapi_sitemap/cli.py
fastapi_sitemap/sitemap.py
fastapi_sitemap-1.0.4.dist-info/METADATA
fastapi_sitemap-1.0.4.dist-info/WHEEL
fastapi_sitemap-1.0.4.dist-info/entry_points.txt
fastapi_sitemap-1.0.4.dist-info/RECORD
