Metadata-Version: 2.3
Name: fastapi-sitemap
Version: 1.0.4
Summary: Zero‑config sitemap generator & route for FastAPI / Starlette apps
License: MIT
Keywords: fastapi,sitemap,seo,starlette,asgi
Author: Erik Aronesty
Author-email: erik@example.com
Requires-Python: >=3.9
Classifier: Framework :: AsyncIO
Classifier: Framework :: FastAPI
Classifier: License :: OSI Approved :: MIT License
Classifier: Programming Language :: Python :: 3
Classifier: Programming Language :: Python :: 3.9
Classifier: Programming Language :: Python :: 3.10
Classifier: Programming Language :: Python :: 3.11
Classifier: Programming Language :: Python :: 3.12
Classifier: Programming Language :: Python :: 3.13
Classifier: Programming Language :: Python :: 3 :: Only
Classifier: Typing :: Typed
Requires-Dist: fastapi (>=0.115.12,<0.116.0)
Project-URL: Homepage, https://github.com/q32/fastapi-sitemap
